README.rst
setup.py
django_static_libs.egg-info/PKG-INFO
django_static_libs.egg-info/SOURCES.txt
django_static_libs.egg-info/dependency_links.txt
django_static_libs.egg-info/top_level.txt
static_libs/__init__.py
static_libs/static/libs/bootstrap/3.0/css/bootstrap-theme.css
static_libs/static/libs/bootstrap/3.0/css/bootstrap-theme.min.css
static_libs/static/libs/bootstrap/3.0/css/bootstrap.css
static_libs/static/libs/bootstrap/3.0/css/bootstrap.min.css
static_libs/static/libs/bootstrap/3.0/fonts/glyphicons-halflings-regular.eot
static_libs/static/libs/bootstrap/3.0/fonts/glyphicons-halflings-regular.svg
static_libs/static/libs/bootstrap/3.0/fonts/glyphicons-halflings-regular.ttf
static_libs/static/libs/bootstrap/3.0/fonts/glyphicons-halflings-regular.woff
static_libs/static/libs/bootstrap/3.0/fonts/glyphiconshalflings-regular.eot
static_libs/static/libs/bootstrap/3.0/fonts/glyphiconshalflings-regular.otf
static_libs/static/libs/bootstrap/3.0/fonts/glyphiconshalflings-regular.svg
static_libs/static/libs/bootstrap/3.0/fonts/glyphiconshalflings-regular.ttf
static_libs/static/libs/bootstrap/3.0/fonts/glyphiconshalflings-regular.woff
static_libs/static/libs/bootstrap/3.0/js/bootstrap.js
static_libs/static/libs/bootstrap/3.0/js/bootstrap.min.js
static_libs/static/libs/fontello/css/animation.css
static_libs/static/libs/fontello/css/fontello-codes.css
static_libs/static/libs/fontello/css/fontello-embedded.css
static_libs/static/libs/fontello/css/fontello-ie7-codes.css
static_libs/static/libs/fontello/css/fontello-ie7.css
static_libs/static/libs/fontello/css/fontello.css
static_libs/static/libs/fontello/css/native-colors.scss
static_libs/static/libs/fontello/font/fontello.eot
static_libs/static/libs/fontello/font/fontello.svg
static_libs/static/libs/fontello/font/fontello.ttf
static_libs/static/libs/fontello/font/fontello.woff
static_libs/static/libs/jgrowl/x.x.x/jquery.jgrowl.css
static_libs/static/libs/jgrowl/x.x.x/jquery.jgrowl.min.js
static_libs/static/libs/jquery-ui/1.10.3/AUTHORS.txt
static_libs/static/libs/jquery-ui/1.10.3/Gruntfile.js
static_libs/static/libs/jquery-ui/1.10.3/MANIFEST
