Metadata-Version: 1.0
Name: django-static-libs
Version: 0.1.6
Summary: UNKNOWN
Home-page: https://github.com/dimka665/django-static-libs
Author: Dmitry Voronin
Author-email: dimka665@gmail.com
License: BSD
Platform: UNKNOWN
